kamzik3/__init__.py
kamzik3/constants.py
kamzik3/resource_kamzik3_rc.py
kamzik3/devices/__init__.py
kamzik3/devices/attribute.py
kamzik3/devices/attributeLogger.py
kamzik3/devices/device.py
kamzik3/devices/deviceBaumerLaserSensor.py
kamzik3/devices/deviceChannel.py
kamzik3/devices/deviceClient.py
kamzik3/devices/deviceCv2.py
kamzik3/devices/deviceEigerP11.py
kamzik3/devices/deviceEpos.py
kamzik3/devices/deviceFileServer.py
kamzik3/devices/deviceFileSync.py
kamzik3/devices/deviceGalil.py
kamzik3/devices/deviceGalilMotor.py
kamzik3/devices/deviceInficonQcm.py
kamzik3/devices/deviceKaraboBridge.py
kamzik3/devices/deviceKohzu.py
kamzik3/devices/deviceLexium.py
kamzik3/devices/deviceLogParser.py
kamzik3/devices/deviceMaxiGauge.py
kamzik3/devices/deviceNiCard.py
kamzik3/devices/deviceOsLibrary.py
kamzik3/devices/devicePeakTech.py
kamzik3/devices/devicePi.py
kamzik3/devices/devicePicoscale.py
kamzik3/devices/devicePort.py
kamzik3/devices/deviceProbusV.py
kamzik3/devices/devicePublisher.py
kamzik3/devices/deviceRheodyneBox.py
kamzik3/devices/deviceSavedAttributes.py
kamzik3/devices/deviceScreenGrabber.py
kamzik3/devices/deviceServer.py
kamzik3/devices/deviceSession.py
kamzik3/devices/deviceSmaractMcs1.py
kamzik3/devices/deviceSmaractMcs2.py
kamzik3/devices/deviceSmarpodEcm.py
kamzik3/devices/deviceSocket.py
kamzik3/devices/deviceTango.py
kamzik3/devices/deviceThermoCube.py
kamzik3/devices/deviceVirtualDirectory.py
kamzik3/devices/deviceWorker.py
kamzik3/devices/deviceZled.py
kamzik3/devices/observer.py
kamzik3/devices/subject.py
kamzik3/devices/dummy/__init__.py
kamzik3/devices/dummy/deviceDummy.py
kamzik3/devices/dummy/deviceDummyEiger.py
kamzik3/devices/dummy/dummyDetector.py
kamzik3/devices/dummy/dummyFeatureTestDevice.py
kamzik3/devices/dummy/dummyInficonQcm.py
kamzik3/devices/dummy/dummyMotor.py
kamzik3/devices/dummy/dummyScanner.py
kamzik3/devices/dummy/dummyShutter.py
kamzik3/devices/dummy/dummyTangoDevice.py
kamzik3/devices/general/__init__.py
kamzik3-0.7.10.dist-info/LICENSE
kamzik3-0.7.10.dist-info/METADATA
kamzik3-0.7.10.dist-info/WHEEL
kamzik3-0.7.10.dist-info/top_level.txt
kamzik3-0.7.10.dist-info/RECORD
