Metadata-Version: 2.1
Name: kamzik3
Version: 0.7.10
Summary: Device controlling framework
Home-page: https://gitlab.desy.de/cfel-sc/kamzik3
Author: Martin Domaracky
Author-email: sc@cfel.de
License: UNKNOWN
Platform: UNKNOWN
Classifier: Programming Language :: Python :: 3.8
Classifier: Programming Language :: Python :: 3.9
Classifier: Operating System :: OS Independent
Classifier: Development Status :: 3 - Alpha
Classifier: Topic :: Software Development :: Libraries :: Python Modules
Classifier: License :: OSI Approved :: GNU General Public License v3 or later (GPLv3+)
Classifier: Natural Language :: English
Classifier: Intended Audience :: Science/Research
Requires-Python: >=3.8, <3.10
Requires-Dist: numpy (>=1.16)
Requires-Dist: pyzmq (>=18.0)
Requires-Dist: pint (>=0.19.2)
Requires-Dist: bidict (>=0.18)
Requires-Dist: pyqt5 (>=5.15.0)
Requires-Dist: pyqtgraph (>=0.11.0)
Requires-Dist: pyserial (>=3.4)
Requires-Dist: oyaml (>=0.9)
Requires-Dist: psutil (>=5.6.0)
Requires-Dist: natsort (>=7.0.1)
Requires-Dist: reportlab (>=3.5.42)
Requires-Dist: pandas (>=1.0.4)
Requires-Dist: tables (>=3.6.1)
Requires-Dist: h5py (>=3.2.1)
